MANIFEST.in
README
setup.cfg
setup.py
sphinxcontrib/__init__.py
sphinxcontrib/mercurial/__init__.py
sphinxcontrib/mercurial/hg_changelog.py
sphinxcontrib/mercurial/hg_version.py
sphinxcontrib_mercurial.egg-info/PKG-INFO
sphinxcontrib_mercurial.egg-info/SOURCES.txt
sphinxcontrib_mercurial.egg-info/dependency_links.txt
sphinxcontrib_mercurial.egg-info/namespace_packages.txt
sphinxcontrib_mercurial.egg-info/not-zip-safe
sphinxcontrib_mercurial.egg-info/requires.txt
sphinxcontrib_mercurial.egg-info/top_level.txt