Metadata-Version: 1.1
Name: sphinxcontrib-mercurial
Version: 0.2
Summary: Sphinx "mercurial" extension
Home-page: http://bitbucket.org/cointoss1973/sphinxcontrib-mercurial
Author: Takayuki KONDO
Author-email: tkondou@gmail.com
License: GPLv3
Download-URL: http://pypi.python.org/pypi/sphinxcontrib-mercurial
Platform: any
Classifier: Development Status :: 4 - Beta
Classifier: Environment :: Console
Classifier: Environment :: Web Environment
Classifier: Intended Audience :: Developers
Classifier: License :: OSI Approved :: GNU General Public License v3 or later (GPLv3+)
Classifier: Operating System :: OS Independent
Classifier: Programming Language :: Python
Classifier: Topic :: Documentation
Classifier: Topic :: Utilities
